stupa/__init__.py
stupa/commons/__init__.py
stupa/commons/base_response.py
stupa/commons/id_generation.py
stupa/commons/paginator.py
stupa/commons/request_utils.py
stupa/commons/third_party_api_response.py
stupa/commons/commands/__init__.py
stupa/commons/commands/alert_commands.py
stupa/exceptions/__init__.py
stupa/exceptions/api_exceptions.py
stupa/exceptions/version_mismatch_exception.py
stupa/middlewares/__init__.py
stupa/middlewares/api_exception_middleware.py
stupa/utils/__init__.py
stupa/utils/class_utility.py
stupa/utils/request_adapter.py
stupa-0.1.2.dist-info/METADATA
stupa-0.1.2.dist-info/WHEEL
stupa-0.1.2.dist-info/licenses/LICENSE
stupa-0.1.2.dist-info/RECORD
