Metadata-Version: 2.3
Name: stupa
Version: 0.1.2
Summary: A Django API toolkit for response utilities, exceptions, middleware, and alert handlers.
Author-email: Ram Suthar <ramsuthar305@gmail.com>
License: MIT
Classifier: Development Status :: 3 - Alpha
Classifier: Framework :: Django
Classifier: Intended Audience :: Developers
Classifier: License :: OSI Approved :: MIT License
Classifier: Programming Language :: Python :: 3
Requires-Python: >=3.8
Requires-Dist: django
